LICENSE
mpc_obscodes/__init__.py
mpc_obscodes/compare.py
mpc_obscodes/fetch.py
mpc_obscodes/obscodes_extended.json
mpc_obscodes/obscodes_extended.md5
mpc_obscodes/tests/__init__.py
mpc_obscodes/tests/test_compare.py
mpc_obscodes/tests/test_fetch.py
mpc_obscodes/tests/test_mpc_obscodes.py
mpc_obscodes-2025.10.1.dist-info/licenses/LICENSE
mpc_obscodes-2025.10.1.dist-info/METADATA
mpc_obscodes-2025.10.1.dist-info/WHEEL
mpc_obscodes-2025.10.1.dist-info/top_level.txt
mpc_obscodes-2025.10.1.dist-info/RECORD
