Metadata-Version: 2.4
Name: mpc_obscodes
Version: 2025.10.1
Summary: Minor Planet Center Observatory Codes
Author-email: B612 Asteroid Institute <info@b612foundation.org>
License: MIT
Requires-Python: >=3.7
License-File: LICENSE
Provides-Extra: tests
Requires-Dist: pytest; extra == "tests"
Dynamic: license-file
